README.md
setup.py
s_and_p_500/__init__.py
s_and_p_500/get.py
s_and_p_500.egg-info/PKG-INFO
s_and_p_500.egg-info/SOURCES.txt
s_and_p_500.egg-info/dependency_links.txt
s_and_p_500.egg-info/requires.txt
s_and_p_500.egg-info/top_level.txt