Metadata-Version: 2.1
Name: s-and-p-500
Version: 0.0.1
Summary: Retrieve S&P500 prices
Home-page: https://github.com/BBScholar/s_and_p_500.git
Author: Ben Scholar
Author-email: bens@digitalman.com
License: UNKNOWN
Platform: UNKNOWN
Classifier: Programming Language :: Python :: 3
Classifier: License :: OSI Approved :: MIT License
Classifier: Operating System :: OS Independent
Requires-Python: >=3.5
